flask_paginated_response
tests
