Metadata-Version: 1.1
Name: Flask-Paginated-Response
Version: 1.0.1
Summary: Response maker for Flask with RFC Standards such as Link Headers
Home-page: https://github.com/vrcmarcos/flask-paginated-response
Author: Marcos Cardoso
Author-email: vrcmarcos@gmail.com
License: MIT
Platform: any
Classifier: Environment :: Web Environment
Classifier: Intended Audience :: Developers
Classifier: Operating System :: OS Independent
Classifier: Programming Language :: Python
Classifier: Topic :: Software Development :: Libraries :: Python Modules
